Metadata-Version: 2.1
Name: jrFile
Version: 0.0.2
Summary: 不会读写文件吗？就得会这个库
Home-page: https://github.com/
Author: Jianrui Li
Author-email: lijianrui7560@qq.com
License: UNKNOWN
Platform: UNKNOWN
Classifier: Programming Language :: Python :: 3
Classifier: License :: OSI Approved :: MIT License
Classifier: Operating System :: OS Independent
